[
    {
        "message": "Программа запущена",
        "timestamp": "20:18:58",
        "type": "SYSTEM"
    },
    {
        "message": "Программа остановлена",
        "timestamp": "20:23:45",
        "type": "SYSTEM"
    },
    {
        "message": "Программа запущена",
        "timestamp": "20:27:14",
        "type": "SYSTEM"
    },
    {
        "message": "Программа остановлена",
        "timestamp": "20:28:00",
        "type": "SYSTEM"
    },
    {
        "message": "Программа запущена",
        "timestamp": "20:29:40",
        "type": "SYSTEM"
    },
    {
        "message": "Программа остановлена",
        "timestamp": "20:42:07",
        "type": "SYSTEM"
    }
]
